turnwise/__init__.py
turnwise/config.py
turnwise/evaluate.py
turnwise/py.typed
turnwise/cli/__init__.py
turnwise/cli/commands.py
turnwise/cli/main.py
turnwise/core/__init__.py
turnwise/core/evaluator.py
turnwise/data/__init__.py
turnwise/data/dataset.py
turnwise/data/types.py
turnwise/metrics/__init__.py
turnwise/metrics/base.py
turnwise/metrics/conversation/__init__.py
turnwise/metrics/conversation/coherence.py
turnwise/metrics/conversation/length.py
turnwise/metrics/llm/__init__.py
turnwise/metrics/llm/helpfulness.py
turnwise/metrics/llm/quality.py
turnwise/metrics/llm/safety.py
turnwise/metrics/relevance/__init__.py
turnwise/metrics/relevance/response_relevance.py
turnwise/utils/__init__.py
turnwise/utils/logging.py
turnwise-0.1.0.dist-info/METADATA
turnwise-0.1.0.dist-info/WHEEL
turnwise-0.1.0.dist-info/entry_points.txt
turnwise-0.1.0.dist-info/RECORD
