Metadata-Version: 2.4
Name: turnwise
Version: 0.1.0
Summary: A modern Python library for evaluating multi-turn chatbot conversations
Author-email: hericles.me@gmail.com
Requires-Python: >=3.12
Requires-Dist: anthropic>=0.68.0
Requires-Dist: click>=8.0.0
Requires-Dist: openai>=1.108.2
Requires-Dist: pydantic-ai>=1.0.10
Requires-Dist: python-dotenv>=1.0.0
